fastmigrate/__init__.py
fastmigrate/cli.py
fastmigrate/core.py
fastmigrate/migrations.py
fastmigrate-0.4.0.dist-info/METADATA
fastmigrate-0.4.0.dist-info/WHEEL
fastmigrate-0.4.0.dist-info/entry_points.txt
fastmigrate-0.4.0.dist-info/top_level.txt
fastmigrate-0.4.0.dist-info/RECORD
