Metadata-Version: 2.4
Name: fastmigrate
Version: 0.4.0
Summary: Structured migration of data in SQLite databases
License: MIT
Requires-Python: >=3.10
Requires-Dist: apswutils>=0.0.2
